shapelyutils/__init__.py
shapelyutils/iterator.py
shapelyutils-0.2.0.dist-info/LICENSE
shapelyutils-0.2.0.dist-info/METADATA
shapelyutils-0.2.0.dist-info/WHEEL
shapelyutils-0.2.0.dist-info/top_level.txt
shapelyutils-0.2.0.dist-info/RECORD
