Metadata-Version: 2.1
Name: shapelyutils
Version: 0.2.0
Summary: Utilities to make life with shapely easier
Home-page: https://bitbucket.com/steerpath/shapelyutils-python
Author: Mikko Virkkilä
Author-email: mikko.virkkila@steerpath.com
License: UNKNOWN
Platform: UNKNOWN
Classifier: Programming Language :: Python :: 3
Classifier: License :: Other/Proprietary License
Classifier: Operating System :: OS Independent
